{
    "type": "FeatureCollection",
    "features": [
        {
            "type": "Feature",
            "geometry": {
                "type": "Point",
                "coordinates": [
                    138.584012095684,
                    -35.0344221219038,
                    0
                ]
            },
            "properties": {
                "feedType": "incident",
                "sourceTitle": "EVE ROAD, BELLEVUE HEIGHTS",
                "category": "other",
                "subcategory": "fire alarm",
                "status": "going",
                "id": "1397575",
                "created": "2020-12-21T17:27:00+10:30",
                "updated": "2020-12-21T17:27:00+10:30",
                "title": "incident: other"
            },
            "id": "1397575"
        },
        {
            "type": "Feature",
            "geometry": {
                "type": "Point",
                "coordinates": [
                    138.615528816446,
                    -35.2437173693988,
                    0
                ]
            },
            "properties": {
                "feedType": "incident",
                "sourceTitle": "PENNYS HILL ROAD, THE RANGE",
                "category": "other",
                "subcategory": "helicopter landing",
                "status": "going",
                "id": "1397570",
                "created": "2020-12-21T16:30:00+10:30",
                "updated": "2020-12-21T16:30:00+10:30",
                "title": "incident: other"
            },
            "id": "1397570"
        },
        {
            "type": "Feature",
            "geometry": {
                "type": "Point",
                "coordinates": [
                    138.615528816446,
                    -35.2437173693988,
                    0
                ]
            },
            "properties": {
                "feedType": "incident",
                "sourceTitle": "PENNYS HILL ROAD, THE RANGE",
                "category": "vehicle",
                "subcategory": "vehicle accident",
                "status": "going",
                "id": "1397567",
                "created": "2020-12-21T16:20:00+10:30",
                "updated": "2020-12-21T16:20:00+10:30",
                "title": "incident: vehicle"
            },
            "id": "1397567"
        },
        {
            "type": "Feature",
            "geometry": {
                "type": "Point",
                "coordinates": [
                    138.354626979608,
                    -33.2608313613368,
                    0
                ]
            },
            "properties": {
                "feedType": "incident",
                "sourceTitle": "PARK TERRACE, GLADSTONE",
                "category": "other",
                "subcategory": "assist other agencies",
                "status": "complete",
                "id": "1397566",
                "created": "2020-12-21T16:19:00+10:30",
                "updated": "2020-12-21T16:19:00+10:30",
                "title": "incident: other"
            },
            "id": "1397566"
        },
        {
            "type": "Feature",
            "geometry": {
                "type": "Point",
                "coordinates": [
                    136.10378474838,
                    -34.3679386780594,
                    0
                ]
            },
            "properties": {
                "feedType": "incident",
                "sourceTitle": "THOMPSON STREET, TUMBY BAY",
                "category": "other",
                "subcategory": "assist other agencies",
                "status": "complete",
                "id": "1397565",
                "created": "2020-12-21T15:59:00+10:30",
                "updated": "2020-12-21T15:59:00+10:30",
                "title": "incident: other"
            },
            "id": "1397565"
        },
        {
            "type": "Feature",
            "geometry": {
                "type": "Point",
                "coordinates": [
                    138.800981070765,
                    -35.0214219894831,
                    0
                ]
            },
            "properties": {
                "feedType": "incident",
                "sourceTitle": "MOUNT BARKER ROAD, HAHNDORF",
                "category": "vehicle",
                "subcategory": "vehicle fire",
                "status": "complete",
                "id": "1397553",
                "created": "2020-12-21T13:39:00+10:30",
                "updated": "2020-12-21T13:39:00+10:30",
                "title": "incident: vehicle"
            },
            "id": "1397553"
        },
        {
            "type": "Feature",
            "geometry": {
                "type": "Point",
                "coordinates": [
                    138.584012095684,
                    -35.0344221219038,
                    0
                ]
            },
            "properties": {
                "feedType": "incident",
                "sourceTitle": "EVE ROAD, BELLEVUE HEIGHTS",
                "category": "other",
                "subcategory": "fire alarm",
                "status": "complete",
                "id": "1397574",
                "created": "2020-12-21T17:06:00+10:30",
                "updated": "2020-12-21T17:06:00+10:30",
                "title": "incident: other"
            },
            "id": "1397574"
        },
        {
            "type": "Feature",
            "geometry": {
                "type": "Point",
                "coordinates": [
                    137.793354416223,
                    -34.9113106282138,
                    0
                ]
            },
            "properties": {
                "feedType": "incident",
                "sourceTitle": "SOUTH TERRACE, STANSBURY",
                "category": "fire",
                "subcategory": "grass fire",
                "status": "complete",
                "id": "1397560",
                "created": "2020-12-21T15:39:00+10:30",
                "updated": "2020-12-21T15:39:00+10:30",
                "title": "incident: fire"
            },
            "id": "1397560"
        },
        {
            "type": "Feature",
            "geometry": {
                "type": "Point",
                "coordinates": [
                    138.615319305787,
                    -35.0223750958314,
                    0
                ]
            },
            "properties": {
                "feedType": "incident",
                "sourceTitle": "BRIGHTON PARADE, BLACKWOOD",
                "category": "other",
                "subcategory": "private alarm",
                "status": "complete",
                "id": "1397556",
                "created": "2020-12-21T14:17:00+10:30",
                "updated": "2020-12-21T14:17:00+10:30",
                "title": "incident: other"
            },
            "id": "1397556"
        },
        {
            "type": "Feature",
            "geometry": {
                "type": "Point",
                "coordinates": [
                    138.625256135464,
                    -35.0768141047352,
                    0
                ]
            },
            "properties": {
                "feedType": "incident",
                "sourceTitle": "MAIN ROAD, CHANDLERS HILL",
                "category": "other",
                "subcategory": "animal rescue",
                "status": "complete",
                "id": "1397550",
                "created": "2020-12-21T12:55:00+10:30",
                "updated": "2020-12-21T12:55:00+10:30",
                "title": "incident: other"
            },
            "id": "1397550"
        },
        {
            "type": "Feature",
            "geometry": {
                "type": "Point",
                "coordinates": [
                    138.664410027157,
                    -34.6742403232062,
                    0
                ]
            },
            "properties": {
                "feedType": "incident",
                "sourceTitle": "PRESIDENT AVENUE, ANDREWS FARM",
                "category": "other",
                "subcategory": "private alarm",
                "status": "complete",
                "id": "1397534",
                "created": "2020-12-21T10:39:00+10:30",
                "updated": "2020-12-21T10:39:00+10:30",
                "title": "incident: other"
            },
            "id": "1397534"
        },
        {
            "type": "Feature",
            "geometry": {
                "type": "Point",
                "coordinates": [
                    136.866070116166,
                    -30.447416353488,
                    0
                ]
            },
            "properties": {
                "feedType": "incident",
                "sourceTitle": "ROXBY DOWNS",
                "category": "other",
                "subcategory": "private alarm",
                "status": "complete",
                "id": "1397518",
                "created": "2020-12-21T08:48:00+10:30",
                "updated": "2020-12-21T08:48:00+10:30",
                "title": "incident: other"
            },
            "id": "1397518"
        },
        {
            "type": "Feature",
            "geometry": {
                "type": "Point",
                "coordinates": [
                    134.757107512694,
                    -29.0167839678272,
                    0
                ]
            },
            "properties": {
                "feedType": "incident",
                "sourceTitle": "EYRE STREET, COOBER PEDY",
                "category": "structure",
                "subcategory": "building fire",
                "status": "complete",
                "id": "1397507",
                "created": "2020-12-21T07:44:00+10:30",
                "updated": "2020-12-21T07:44:00+10:30",
                "title": "incident: structure"
            },
            "id": "1397507"
        },
        {
            "type": "Feature",
            "geometry": {
                "type": "Point",
                "coordinates": [
                    136.908033070216,
                    -30.5610926821419,
                    0
                ]
            },
            "properties": {
                "feedType": "incident",
                "sourceTitle": "CLAYTON COURT, ROXBY DOWNS",
                "category": "other",
                "subcategory": "rubbish fire",
                "status": "complete",
                "id": "1397493",
                "created": "2020-12-21T00:53:00+10:30",
                "updated": "2020-12-21T00:53:00+10:30",
                "title": "incident: other"
            },
            "id": "1397493"
        }
    ]
}