{
    "type": "FeatureCollection",
    "features": [
        {
            "type": "Feature",
            "geometry": {
                "type": "Point",
                "coordinates": [
                    146.36033831756265,
                    -41.177619503864285
                ]
            },
            "properties": {
                "feedType": "incident",
                "sourceTitle": "Rooke Street, DEVONPORT",
                "category": "other",
                "subcategory": "alarm",
                "status": "going",
                "id": "20027508Rooke Street, DEVONPORT",
                "created": "2020-10-03T00:21:00+10:00",
                "updated": "2020-10-03T00:21:00+10:00",
                "size": 0,
                "title": "incident: other"
            },
            "id": "20027508"
        },
        {
            "type": "Feature",
            "geometry": {
                "type": "Point",
                "coordinates": [
                    147.31517279036947,
                    -42.914055053474506
                ]
            },
            "properties": {
                "feedType": "incident",
                "sourceTitle": "Olinda Grove, MOUNT NELSON",
                "category": "fire",
                "subcategory": "fire incident",
                "status": "going",
                "id": "20027507Olinda Grove, MOUNT NELSON",
                "created": "2020-10-02T23:56:00+10:00",
                "updated": "2020-10-02T23:56:00+10:00",
                "size": 0,
                "title": "incident: fire"
            },
            "id": "20027507"
        },
        {
            "type": "Feature",
            "geometry": {
                "type": "Point",
                "coordinates": [
                    148.16677171089322,
                    -41.32404771880012
                ]
            },
            "properties": {
                "feedType": "incident",
                "sourceTitle": "Fuel Reduction Burn Launceston Creek, St Helens",
                "category": "other",
                "subcategory": "fuel reduction burn",
                "status": "going",
                "id": "20027180Fuel Reduction Burn Launceston Creek, St Helens",
                "created": "2020-10-02T15:02:00+10:00",
                "updated": "2020-10-02T15:02:00+10:00",
                "size": 875,
                "title": "incident: other"
            },
            "id": "20027180"
        }
    ]
}