{
    "type": "FeatureCollection",
    "features": [
        {
            "type": "Feature",
            "geometry": {
                "type": "Point",
                "sm_coordinates": "no",
                "coordinates": [
                    115.59304,
                    -31.343548
                ]
            },
            "properties": {
                "feedType": "incident",
                "sourceTitle": "WOODRIDGE",
                "category": "fire",
                "subcategory": "burn off",
                "status": "active",
                "id": "2028825-480954",
                "created": "2020-05-18T07:50:25+08:00",
                "updated": "2020-05-18T07:50:25+08:00",
                "location": "WOODRIDGE",
                "size": "",
                "description": "Burn Off",
                "title": "incident: fire"
            }
        },
        {
            "type": "Feature",
            "geometry": {
                "type": "Point",
                "sm_coordinates": "no",
                "coordinates": [
                    115.538895,
                    -31.298067
                ]
            },
            "properties": {
                "feedType": "incident",
                "sourceTitle": "GABBADAH",
                "category": "fire",
                "subcategory": "burn off",
                "status": "active",
                "id": "2028848-480967",
                "created": "2020-05-18T08:21:24+08:00",
                "updated": "2020-05-18T08:21:24+08:00",
                "location": "GABBADAH",
                "size": "",
                "description": "Burn Off",
                "title": "incident: fire"
            }
        },
        {
            "type": "Feature",
            "geometry": {
                "type": "Point",
                "sm_coordinates": "no",
                "coordinates": [
                    116.02195,
                    -32.097023
                ]
            },
            "properties": {
                "feedType": "incident",
                "sourceTitle": "KELMSCOTT",
                "category": "fire",
                "subcategory": "burn off",
                "status": "active",
                "id": "2028829-480956",
                "created": "2020-05-18T07:55:18+08:00",
                "updated": "2020-05-18T07:55:18+08:00",
                "location": "KELMSCOTT",
                "size": "",
                "description": "Burn Off",
                "title": "incident: fire"
            }
        },
        {
            "type": "Feature",
            "geometry": {
                "type": "Point",
                "sm_coordinates": "no",
                "coordinates": [
                    116.02823,
                    -31.559685
                ]
            },
            "properties": {
                "feedType": "incident",
                "sourceTitle": "LOWER CHITTERING",
                "category": "fire",
                "subcategory": "burn off",
                "status": "active",
                "id": "2028808-480949",
                "created": "2020-05-18T07:20:06+08:00",
                "updated": "2020-05-18T07:20:06+08:00",
                "location": "LOWER CHITTERING",
                "size": "",
                "description": "Burn Off",
                "title": "incident: fire"
            }
        },
        {
            "type": "Feature",
            "geometry": {
                "type": "Point",
                "sm_coordinates": "no",
                "coordinates": [
                    116.03199,
                    -32.146156
                ]
            },
            "properties": {
                "feedType": "incident",
                "sourceTitle": "BEDFORDALE",
                "category": "fire",
                "subcategory": "burn off",
                "status": "active",
                "id": "2028930-480993",
                "created": "2020-05-18T09:36:16+08:00",
                "updated": "2020-05-18T09:36:16+08:00",
                "location": "BEDFORDALE",
                "size": "",
                "description": "Burn Off",
                "title": "incident: fire"
            }
        },
        {
            "type": "Feature",
            "geometry": {
                "type": "Point",
                "sm_coordinates": "no",
                "coordinates": [
                    116.07149,
                    -32.191994
                ]
            },
            "properties": {
                "feedType": "incident",
                "sourceTitle": "BEDFORDALE",
                "category": "fire",
                "subcategory": "burn off",
                "status": "active",
                "id": "2029015-481024",
                "created": "2020-05-18T11:14:43+08:00",
                "updated": "2020-05-18T11:17:04+08:00",
                "location": "BEDFORDALE",
                "size": "",
                "description": "Burn Off",
                "title": "incident: fire"
            }
        },
        {
            "type": "Feature",
            "geometry": {
                "type": "Point",
                "sm_coordinates": "no",
                "coordinates": [
                    115.73893,
                    -31.503784
                ]
            },
            "properties": {
                "feedType": "incident",
                "sourceTitle": "YANCHEP",
                "category": "fire",
                "subcategory": "burn off",
                "status": "active",
                "id": "2029025-481027",
                "created": "2020-05-18T11:35:43+08:00",
                "updated": "2020-05-18T11:44:44+08:00",
                "location": "YANCHEP",
                "size": "",
                "description": "Burn Off",
                "title": "incident: fire"
            }
        },
        {
            "type": "Feature",
            "geometry": {
                "type": "Point",
                "sm_coordinates": "no",
                "coordinates": [
                    115.54058,
                    -31.292377
                ]
            },
            "properties": {
                "feedType": "incident",
                "sourceTitle": "GABBADAH",
                "category": "fire",
                "subcategory": "burn off",
                "status": "active",
                "id": "2029104-481050",
                "created": "2020-05-18T13:16:13+08:00",
                "updated": "2020-05-18T13:16:13+08:00",
                "location": "GABBADAH",
                "size": "",
                "description": "Burn Off",
                "title": "incident: fire"
            }
        },
        {
            "type": "Feature",
            "geometry": {
                "type": "Point",
                "sm_coordinates": "no",
                "coordinates": [
                    115.65964,
                    -32.7507
                ]
            },
            "properties": {
                "feedType": "incident",
                "sourceTitle": "HERRON",
                "category": "fire",
                "subcategory": "burn off",
                "status": "active",
                "id": "2028839-480961",
                "created": "2020-05-18T08:06:04+08:00",
                "updated": "2020-05-18T08:06:04+08:00",
                "location": "HERRON",
                "size": "",
                "description": "Burn Off",
                "title": "incident: fire"
            }
        },
        {
            "type": "Feature",
            "geometry": {
                "type": "Point",
                "sm_coordinates": "no",
                "coordinates": [
                    115.7049,
                    -33.3023
                ]
            },
            "properties": {
                "feedType": "incident",
                "sourceTitle": "AUSTRALIND",
                "category": "fire",
                "subcategory": "burn off",
                "status": "active",
                "id": "2028843-480963",
                "created": "2020-05-18T08:12:26+08:00",
                "updated": "2020-05-18T08:12:26+08:00",
                "location": "AUSTRALIND",
                "size": "",
                "description": "Burn Off",
                "title": "incident: fire"
            }
        },
        {
            "type": "Feature",
            "geometry": {
                "type": "Point",
                "sm_coordinates": "no",
                "coordinates": [
                    115.79006,
                    -31.696047
                ]
            },
            "properties": {
                "feedType": "incident",
                "sourceTitle": "CARRAMAR",
                "category": "fire",
                "subcategory": "burn off",
                "status": "active",
                "id": "2028895-480982",
                "created": "2020-05-18T09:09:56+08:00",
                "updated": "2020-05-18T09:09:56+08:00",
                "location": "CARRAMAR",
                "size": "",
                "description": "Burn Off",
                "title": "incident: fire"
            }
        },
        {
            "type": "Feature",
            "geometry": {
                "type": "Point",
                "sm_coordinates": "no",
                "coordinates": [
                    116.03532,
                    -31.550653
                ]
            },
            "properties": {
                "feedType": "incident",
                "sourceTitle": "LOWER CHITTERING",
                "category": "fire",
                "subcategory": "burn off",
                "status": "active",
                "id": "2028904-480984",
                "created": "2020-05-18T09:14:59+08:00",
                "updated": "2020-05-18T09:14:59+08:00",
                "location": "LOWER CHITTERING",
                "size": "",
                "description": "Burn Off",
                "title": "incident: fire"
            }
        },
        {
            "type": "Feature",
            "geometry": {
                "type": "Point",
                "sm_coordinates": "no",
                "coordinates": [
                    115.68448,
                    -31.317556
                ]
            },
            "properties": {
                "feedType": "incident",
                "sourceTitle": "NEERGABBY",
                "category": "fire",
                "subcategory": "burn off",
                "status": "active",
                "id": "2028935-480997",
                "created": "2020-05-18T09:39:35+08:00",
                "updated": "2020-05-18T09:39:35+08:00",
                "location": "NEERGABBY",
                "size": "",
                "description": "Burn Off",
                "title": "incident: fire"
            }
        },
        {
            "type": "Feature",
            "geometry": {
                "type": "Point",
                "sm_coordinates": "no",
                "coordinates": [
                    115.759125,
                    -32.560238
                ]
            },
            "properties": {
                "feedType": "incident",
                "sourceTitle": "FURNISSDALE",
                "category": "fire",
                "subcategory": "burn off",
                "status": "active",
                "id": "2029036-481030",
                "created": "2020-05-18T11:46:11+08:00",
                "updated": "2020-05-18T11:46:11+08:00",
                "location": "FURNISSDALE",
                "size": "",
                "description": "Burn Off",
                "title": "incident: fire"
            }
        },
        {
            "type": "Feature",
            "geometry": {
                "type": "Point",
                "sm_coordinates": "no",
                "coordinates": [
                    115.85585,
                    -34.04871
                ]
            },
            "properties": {
                "feedType": "incident",
                "sourceTitle": "EAST NANNUP",
                "category": "fire",
                "subcategory": "burn off",
                "status": "active",
                "id": "2028944-481004",
                "created": "2020-05-18T09:54:56+08:00",
                "updated": "2020-05-18T09:54:56+08:00",
                "location": "EAST NANNUP",
                "size": "",
                "description": "Burn Off",
                "title": "incident: fire"
            }
        },
        {
            "type": "Feature",
            "geometry": {
                "type": "Point",
                "sm_coordinates": "no",
                "coordinates": [
                    116.12891,
                    -32.10995
                ]
            },
            "properties": {
                "feedType": "incident",
                "sourceTitle": "KARRAGULLEN",
                "category": "fire",
                "subcategory": "burn off",
                "status": "active",
                "id": "2028939-481000",
                "created": "2020-05-18T09:47:38+08:00",
                "updated": "2020-05-18T09:47:38+08:00",
                "location": "KARRAGULLEN",
                "size": "",
                "description": "Burn Off",
                "title": "incident: fire"
            }
        },
        {
            "type": "Feature",
            "geometry": {
                "type": "Point",
                "sm_coordinates": "no",
                "coordinates": [
                    115.86269,
                    -32.18255
                ]
            },
            "properties": {
                "feedType": "incident",
                "sourceTitle": "WANDI",
                "category": "fire",
                "subcategory": "burn off",
                "status": "active",
                "id": "2029029-481028",
                "created": "2020-05-18T11:37:08+08:00",
                "updated": "2020-05-18T11:37:08+08:00",
                "location": "WANDI",
                "size": "",
                "description": "Burn Off",
                "title": "incident: fire"
            }
        },
        {
            "type": "Feature",
            "geometry": {
                "type": "Point",
                "sm_coordinates": "no",
                "coordinates": [
                    116.05893,
                    -31.395208
                ]
            },
            "properties": {
                "feedType": "incident",
                "sourceTitle": "BINDOON",
                "category": "fire",
                "subcategory": "burn off",
                "status": "active",
                "id": "2028866-480973",
                "created": "2020-05-18T08:39:07+08:00",
                "updated": "2020-05-18T08:39:07+08:00",
                "location": "BINDOON",
                "size": "",
                "description": "Burn Off",
                "title": "incident: fire"
            }
        },
        {
            "type": "Feature",
            "geometry": {
                "type": "Point",
                "sm_coordinates": "no",
                "coordinates": [
                    116.20706,
                    -31.90049
                ]
            },
            "properties": {
                "feedType": "incident",
                "sourceTitle": "SAWYERS VALLEY",
                "category": "fire",
                "subcategory": "burn off",
                "status": "active",
                "id": "2028963-481009",
                "created": "2020-05-18T10:19:37+08:00",
                "updated": "2020-05-18T10:19:37+08:00",
                "location": "SAWYERS VALLEY",
                "size": "",
                "description": "Burn Off",
                "title": "incident: fire"
            }
        },
        {
            "type": "Feature",
            "geometry": {
                "type": "Point",
                "sm_coordinates": "no",
                "coordinates": [
                    116.06066,
                    -31.54733
                ]
            },
            "properties": {
                "feedType": "incident",
                "sourceTitle": "LOWER CHITTERING",
                "category": "fire",
                "subcategory": "burn off",
                "status": "active",
                "id": "2028947-481006",
                "created": "2020-05-18T10:00:07+08:00",
                "updated": "2020-05-18T10:00:07+08:00",
                "location": "LOWER CHITTERING",
                "size": "",
                "description": "Burn Off",
                "title": "incident: fire"
            }
        },
        {
            "type": "Feature",
            "geometry": {
                "type": "Point",
                "sm_coordinates": "no",
                "coordinates": [
                    115.66219,
                    -32.749344
                ]
            },
            "properties": {
                "feedType": "incident",
                "sourceTitle": "HERRON",
                "category": "fire",
                "subcategory": "burn off",
                "status": "active",
                "id": "2028845-480965",
                "created": "2020-05-18T08:16:06+08:00",
                "updated": "2020-05-18T08:16:06+08:00",
                "location": "HERRON",
                "size": "",
                "description": "Burn Off",
                "title": "incident: fire"
            }
        },
        {
            "type": "Feature",
            "geometry": {
                "type": "Point",
                "sm_coordinates": "no",
                "coordinates": [
                    116.00133,
                    -32.290672
                ]
            },
            "properties": {
                "feedType": "incident",
                "sourceTitle": "WHITBY",
                "category": "fire",
                "subcategory": "burn off",
                "status": "active",
                "id": "2028838-480960",
                "created": "2020-05-18T08:05:58+08:00",
                "updated": "2020-05-18T08:05:58+08:00",
                "location": "WHITBY",
                "size": "",
                "description": "Burn Off",
                "title": "incident: fire"
            }
        },
        {
            "type": "Feature",
            "geometry": {
                "type": "Point",
                "sm_coordinates": "no",
                "coordinates": [
                    115.883125,
                    -32.13664
                ]
            },
            "properties": {
                "feedType": "incident",
                "sourceTitle": "BANJUP",
                "category": "fire",
                "subcategory": "burn off",
                "status": "active",
                "id": "2028943-481003",
                "created": "2020-05-18T09:54:42+08:00",
                "updated": "2020-05-18T09:54:42+08:00",
                "location": "BANJUP",
                "size": "",
                "description": "Burn Off",
                "title": "incident: fire"
            }
        },
        {
            "type": "Feature",
            "geometry": {
                "type": "Point",
                "sm_coordinates": "no",
                "coordinates": [
                    116.028725,
                    -32.136204
                ]
            },
            "properties": {
                "feedType": "incident",
                "sourceTitle": "MOUNT NASURA",
                "category": "fire",
                "subcategory": "burn off",
                "status": "active",
                "id": "2028853-480968",
                "created": "2020-05-18T08:25:50+08:00",
                "updated": "2020-05-18T08:25:50+08:00",
                "location": "MOUNT NASURA",
                "size": "",
                "description": "Burn Off",
                "title": "incident: fire"
            }
        },
        {
            "type": "Feature",
            "geometry": {
                "type": "Point",
                "sm_coordinates": "no",
                "coordinates": [
                    115.73637,
                    -33.005943
                ]
            },
            "properties": {
                "feedType": "incident",
                "sourceTitle": "MYALUP",
                "category": "fire",
                "subcategory": "bushfire",
                "status": "monitoring",
                "id": "2028278-480709",
                "created": "2020-05-17T05:00:29+08:00",
                "updated": "2020-05-18T12:07:39+08:00",
                "location": "MYALUP",
                "size": "",
                "description": "Bushfire",
                "title": "incident: fire"
            }
        },
        {
            "type": "Feature",
            "geometry": {
                "type": "Point",
                "sm_coordinates": "no",
                "coordinates": [
                    116.124626,
                    -32.105427
                ]
            },
            "properties": {
                "feedType": "incident",
                "sourceTitle": "KARRAGULLEN",
                "category": "fire",
                "subcategory": "burn off",
                "status": "active",
                "id": "2028919-480988",
                "created": "2020-05-18T09:28:14+08:00",
                "updated": "2020-05-18T09:28:14+08:00",
                "location": "KARRAGULLEN",
                "size": "",
                "description": "Burn Off",
                "title": "incident: fire"
            }
        },
        {
            "type": "Feature",
            "geometry": {
                "type": "Point",
                "sm_coordinates": "no",
                "coordinates": [
                    115.83751,
                    -33.43794
                ]
            },
            "properties": {
                "feedType": "incident",
                "sourceTitle": "FERGUSON",
                "category": "fire",
                "subcategory": "burn off",
                "status": "active",
                "id": "2029074-481041",
                "created": "2020-05-18T12:41:02+08:00",
                "updated": "2020-05-18T12:41:02+08:00",
                "location": "FERGUSON",
                "size": "",
                "description": "Burn Off",
                "title": "incident: fire"
            }
        },
        {
            "type": "Feature",
            "geometry": {
                "type": "Point",
                "sm_coordinates": "no",
                "coordinates": [
                    116.01641,
                    -32.103676
                ]
            },
            "properties": {
                "feedType": "incident",
                "sourceTitle": "KELMSCOTT",
                "category": "fire",
                "subcategory": "burn off",
                "status": "active",
                "id": "2028896-480983",
                "created": "2020-05-18T09:10:07+08:00",
                "updated": "2020-05-18T09:10:07+08:00",
                "location": "KELMSCOTT",
                "size": "",
                "description": "Burn Off",
                "title": "incident: fire"
            }
        },
        {
            "type": "Feature",
            "geometry": {
                "type": "Point",
                "sm_coordinates": "no",
                "coordinates": [
                    115.642975,
                    -31.473856
                ]
            },
            "properties": {
                "feedType": "incident",
                "sourceTitle": "TWO ROCKS",
                "category": "fire",
                "subcategory": "burn off",
                "status": "active",
                "id": "2028826-480955",
                "created": "2020-05-18T07:50:53+08:00",
                "updated": "2020-05-18T15:07:34+08:00",
                "location": "TWO ROCKS",
                "size": "",
                "description": "Burn Off",
                "title": "incident: fire"
            }
        },
        {
            "type": "Feature",
            "geometry": {
                "type": "Point",
                "sm_coordinates": "no",
                "coordinates": [
                    116.15338,
                    -31.875141
                ]
            },
            "properties": {
                "feedType": "incident",
                "sourceTitle": "PARKERVILLE",
                "category": "fire",
                "subcategory": "burn off",
                "status": "active",
                "id": "2029062-481033",
                "created": "2020-05-18T11:53:01+08:00",
                "updated": "2020-05-18T11:53:01+08:00",
                "location": "PARKERVILLE",
                "size": "",
                "description": "Burn Off",
                "title": "incident: fire"
            }
        },
        {
            "type": "Feature",
            "geometry": {
                "type": "Point",
                "sm_coordinates": "no",
                "coordinates": [
                    115.06307,
                    -33.634937
                ]
            },
            "properties": {
                "feedType": "incident",
                "sourceTitle": "QUEDJINUP",
                "category": "fire",
                "subcategory": "structure fire",
                "status": "on scene",
                "id": "2029113-481052",
                "created": "2020-05-18T13:32:21+08:00",
                "updated": "2020-05-18T13:48:02+08:00",
                "location": "QUEDJINUP",
                "size": "",
                "description": "Structure Fire",
                "title": "incident: fire"
            }
        },
        {
            "type": "Feature",
            "geometry": {
                "type": "Point",
                "sm_coordinates": "no",
                "coordinates": [
                    115.74299,
                    -33.330795
                ]
            },
            "properties": {
                "feedType": "incident",
                "sourceTitle": "WATERLOO",
                "category": "fire",
                "subcategory": "burn off",
                "status": "active",
                "id": "2028844-480964",
                "created": "2020-05-18T08:16:05+08:00",
                "updated": "2020-05-18T08:16:05+08:00",
                "location": "WATERLOO",
                "size": "",
                "description": "Burn Off",
                "title": "incident: fire"
            }
        },
        {
            "type": "Feature",
            "geometry": {
                "type": "Point",
                "sm_coordinates": "no",
                "coordinates": [
                    115.49598,
                    -31.267796
                ]
            },
            "properties": {
                "feedType": "incident",
                "sourceTitle": "GABBADAH",
                "category": "fire",
                "subcategory": "burn off",
                "status": "active",
                "id": "2028847-480966",
                "created": "2020-05-18T08:18:47+08:00",
                "updated": "2020-05-18T08:18:47+08:00",
                "location": "GABBADAH",
                "size": "",
                "description": "Burn Off",
                "title": "incident: fire"
            }
        },
        {
            "type": "Feature",
            "geometry": {
                "type": "Point",
                "sm_coordinates": "no",
                "coordinates": [
                    116.06672,
                    -32.12281
                ]
            },
            "properties": {
                "feedType": "incident",
                "sourceTitle": "ROLEYSTONE",
                "category": "fire",
                "subcategory": "burn off",
                "status": "active",
                "id": "2028856-480969",
                "created": "2020-05-18T08:27:37+08:00",
                "updated": "2020-05-18T08:27:37+08:00",
                "location": "ROLEYSTONE",
                "size": "",
                "description": "Burn Off",
                "title": "incident: fire"
            }
        },
        {
            "type": "Feature",
            "geometry": {
                "type": "Point",
                "sm_coordinates": "no",
                "coordinates": [
                    116.083206,
                    -31.372046
                ]
            },
            "properties": {
                "feedType": "incident",
                "sourceTitle": "BINDOON",
                "category": "fire",
                "subcategory": "burn off",
                "status": "active",
                "id": "2028964-481010",
                "created": "2020-05-18T10:19:39+08:00",
                "updated": "2020-05-18T10:19:39+08:00",
                "location": "BINDOON",
                "size": "",
                "description": "Burn Off",
                "title": "incident: fire"
            }
        },
        {
            "type": "Feature",
            "geometry": {
                "type": "Point",
                "sm_coordinates": "no",
                "coordinates": [
                    116.06539,
                    -32.154224
                ]
            },
            "properties": {
                "feedType": "incident",
                "sourceTitle": "BEDFORDALE",
                "category": "fire",
                "subcategory": "burn off",
                "status": "active",
                "id": "2028887-480977",
                "created": "2020-05-18T08:56:36+08:00",
                "updated": "2020-05-18T08:56:36+08:00",
                "location": "BEDFORDALE",
                "size": "",
                "description": "Burn Off",
                "title": "incident: fire"
            }
        },
        {
            "type": "Feature",
            "geometry": {
                "type": "Point",
                "sm_coordinates": "no",
                "coordinates": [
                    116.15579,
                    -31.852211
                ]
            },
            "properties": {
                "feedType": "incident",
                "sourceTitle": "STONEVILLE",
                "category": "fire",
                "subcategory": "burn off",
                "status": "active",
                "id": "2028982-481013",
                "created": "2020-05-18T10:32:28+08:00",
                "updated": "2020-05-18T10:32:28+08:00",
                "location": "STONEVILLE",
                "size": "",
                "description": "Burn Off",
                "title": "incident: fire"
            }
        },
        {
            "type": "Feature",
            "geometry": {
                "type": "Point",
                "sm_coordinates": "no",
                "coordinates": [
                    116.06217,
                    -31.563889
                ]
            },
            "properties": {
                "feedType": "incident",
                "sourceTitle": "LOWER CHITTERING",
                "category": "fire",
                "subcategory": "burn off",
                "status": "active",
                "id": "2028889-480978",
                "created": "2020-05-18T08:59:18+08:00",
                "updated": "2020-05-18T08:59:18+08:00",
                "location": "LOWER CHITTERING",
                "size": "",
                "description": "Burn Off",
                "title": "incident: fire"
            }
        },
        {
            "type": "Feature",
            "geometry": {
                "type": "Point",
                "sm_coordinates": "no",
                "coordinates": [
                    116.045746,
                    -32.101692
                ]
            },
            "properties": {
                "feedType": "incident",
                "sourceTitle": "ROLEYSTONE",
                "category": "fire",
                "subcategory": "burn off",
                "status": "active",
                "id": "2028883-480976",
                "created": "2020-05-18T08:51:08+08:00",
                "updated": "2020-05-18T08:51:08+08:00",
                "location": "ROLEYSTONE",
                "size": "",
                "description": "Burn Off",
                "title": "incident: fire"
            }
        },
        {
            "type": "Feature",
            "geometry": {
                "type": "Point",
                "sm_coordinates": "no",
                "coordinates": [
                    115.77215,
                    -32.497887
                ]
            },
            "properties": {
                "feedType": "incident",
                "sourceTitle": "PARKLANDS",
                "category": "fire",
                "subcategory": "burn off",
                "status": "active",
                "id": "2028871-480974",
                "created": "2020-05-18T08:46:20+08:00",
                "updated": "2020-05-18T08:46:20+08:00",
                "location": "PARKLANDS",
                "size": "",
                "description": "Burn Off",
                "title": "incident: fire"
            }
        },
        {
            "type": "Feature",
            "geometry": {
                "type": "Point",
                "sm_coordinates": "no",
                "coordinates": [
                    115.86918,
                    -31.812542
                ]
            },
            "properties": {
                "feedType": "incident",
                "sourceTitle": "LANDSDALE",
                "category": "fire",
                "subcategory": "burn off",
                "status": "active",
                "id": "2028909-480987",
                "created": "2020-05-18T09:23:35+08:00",
                "updated": "2020-05-18T09:23:35+08:00",
                "location": "LANDSDALE",
                "size": "",
                "description": "Burn Off",
                "title": "incident: fire"
            }
        },
        {
            "type": "Feature",
            "geometry": {
                "type": "Point",
                "sm_coordinates": "no",
                "coordinates": [
                    115.772156,
                    -31.701048
                ]
            },
            "properties": {
                "feedType": "incident",
                "sourceTitle": "CARRAMAR",
                "category": "fire",
                "subcategory": "burn off",
                "status": "active",
                "id": "2028934-480996",
                "created": "2020-05-18T09:39:04+08:00",
                "updated": "2020-05-18T09:39:04+08:00",
                "location": "CARRAMAR",
                "size": "",
                "description": "Burn Off",
                "title": "incident: fire"
            }
        },
        {
            "type": "Feature",
            "geometry": {
                "type": "Point",
                "sm_coordinates": "no",
                "coordinates": [
                    115.77805,
                    -31.691694
                ]
            },
            "properties": {
                "feedType": "incident",
                "sourceTitle": "CARRAMAR",
                "category": "fire",
                "subcategory": "burn off",
                "status": "active",
                "id": "2028921-480989",
                "created": "2020-05-18T09:29:25+08:00",
                "updated": "2020-05-18T09:29:25+08:00",
                "location": "CARRAMAR",
                "size": "",
                "description": "Burn Off",
                "title": "incident: fire"
            }
        },
        {
            "type": "Feature",
            "geometry": {
                "type": "Point",
                "sm_coordinates": "no",
                "coordinates": [
                    116.031425,
                    -31.557371
                ]
            },
            "properties": {
                "feedType": "incident",
                "sourceTitle": "LOWER CHITTERING",
                "category": "fire",
                "subcategory": "burn off",
                "status": "active",
                "id": "2028927-480992",
                "created": "2020-05-18T09:35:08+08:00",
                "updated": "2020-05-18T09:35:16+08:00",
                "location": "LOWER CHITTERING",
                "size": "",
                "description": "Burn Off",
                "title": "incident: fire"
            }
        },
        {
            "type": "Feature",
            "geometry": {
                "type": "Point",
                "sm_coordinates": "no",
                "coordinates": [
                    115.72678,
                    -31.60459
                ]
            },
            "properties": {
                "feedType": "incident",
                "sourceTitle": "CARABOODA",
                "category": "fire",
                "subcategory": "burn off",
                "status": "active",
                "id": "2028938-480999",
                "created": "2020-05-18T09:47:22+08:00",
                "updated": "2020-05-18T09:47:22+08:00",
                "location": "CARABOODA",
                "size": "",
                "description": "Burn Off",
                "title": "incident: fire"
            }
        },
        {
            "type": "Feature",
            "geometry": {
                "type": "Point",
                "sm_coordinates": "no",
                "coordinates": [
                    116.192116,
                    -31.894936
                ]
            },
            "properties": {
                "feedType": "incident",
                "sourceTitle": "SAWYERS VALLEY",
                "category": "fire",
                "subcategory": "burn off",
                "status": "active",
                "id": "2028933-480995",
                "created": "2020-05-18T09:38:18+08:00",
                "updated": "2020-05-18T09:38:18+08:00",
                "location": "SAWYERS VALLEY",
                "size": "",
                "description": "Burn Off",
                "title": "incident: fire"
            }
        },
        {
            "type": "Feature",
            "geometry": {
                "type": "Point",
                "sm_coordinates": "no",
                "coordinates": [
                    116.7208,
                    -34.15135
                ]
            },
            "properties": {
                "feedType": "incident",
                "sourceTitle": "CHOWERUP",
                "category": "fire",
                "subcategory": "burn off",
                "status": "active",
                "id": "2029024-481026",
                "created": "2020-05-18T11:33:27+08:00",
                "updated": "2020-05-18T11:33:27+08:00",
                "location": "CHOWERUP",
                "size": "",
                "description": "Burn Off",
                "title": "incident: fire"
            }
        },
        {
            "type": "Feature",
            "geometry": {
                "type": "Point",
                "sm_coordinates": "no",
                "coordinates": [
                    116.02734,
                    -31.734425
                ]
            },
            "properties": {
                "feedType": "incident",
                "sourceTitle": "BULLSBROOK",
                "category": "fire",
                "subcategory": "burn off",
                "status": "active",
                "id": "2029211-481083",
                "created": "2020-05-18T15:22:05+08:00",
                "updated": "2020-05-18T15:22:05+08:00",
                "location": "BULLSBROOK",
                "size": "",
                "description": "Burn Off",
                "title": "incident: fire"
            }
        },
        {
            "type": "Feature",
            "geometry": {
                "type": "Point",
                "sm_coordinates": "no",
                "coordinates": [
                    116.05102,
                    -32.34392
                ]
            },
            "properties": {
                "feedType": "incident",
                "sourceTitle": "JARRAHDALE",
                "category": "fire",
                "subcategory": "burn off",
                "status": "active",
                "id": "2029131-481056",
                "created": "2020-05-18T13:48:36+08:00",
                "updated": "2020-05-18T13:48:36+08:00",
                "location": "JARRAHDALE",
                "size": "",
                "description": "Burn Off",
                "title": "incident: fire"
            }
        },
        {
            "type": "Feature",
            "geometry": {
                "type": "Point",
                "sm_coordinates": "no",
                "coordinates": [
                    116.17979,
                    -31.735134
                ]
            },
            "properties": {
                "feedType": "incident",
                "sourceTitle": "GIDGEGANNUP",
                "category": "fire",
                "subcategory": "burn off",
                "status": "active",
                "id": "2029124-481054",
                "created": "2020-05-18T13:43:16+08:00",
                "updated": "2020-05-18T13:43:16+08:00",
                "location": "GIDGEGANNUP",
                "size": "",
                "description": "Burn Off",
                "title": "incident: fire"
            }
        },
        {
            "type": "Feature",
            "geometry": {
                "type": "Point",
                "sm_coordinates": "no",
                "coordinates": [
                    115.86881,
                    -32.196526
                ]
            },
            "properties": {
                "feedType": "incident",
                "sourceTitle": "WANDI",
                "category": "fire",
                "subcategory": "burn off",
                "status": "active",
                "id": "2028978-481012",
                "created": "2020-05-18T10:29:53+08:00",
                "updated": "2020-05-18T10:29:53+08:00",
                "location": "WANDI",
                "size": "",
                "description": "Burn Off",
                "title": "incident: fire"
            }
        },
        {
            "type": "Feature",
            "geometry": {
                "type": "Point",
                "sm_coordinates": "no",
                "coordinates": [
                    115.88992,
                    -32.142593
                ]
            },
            "properties": {
                "feedType": "incident",
                "sourceTitle": "BANJUP",
                "category": "fire",
                "subcategory": "burn off",
                "status": "active",
                "id": "2029077-481042",
                "created": "2020-05-18T12:43:45+08:00",
                "updated": "2020-05-18T12:43:45+08:00",
                "location": "BANJUP",
                "size": "",
                "description": "Burn Off",
                "title": "incident: fire"
            }
        },
        {
            "type": "Feature",
            "geometry": {
                "type": "Point",
                "sm_coordinates": "no",
                "coordinates": [
                    116.18882,
                    -31.899408
                ]
            },
            "properties": {
                "feedType": "incident",
                "sourceTitle": "SAWYERS VALLEY",
                "category": "fire",
                "subcategory": "burn off",
                "status": "active",
                "id": "2029078-481043",
                "created": "2020-05-18T12:44:13+08:00",
                "updated": "2020-05-18T12:44:13+08:00",
                "location": "SAWYERS VALLEY",
                "size": "",
                "description": "Burn Off",
                "title": "incident: fire"
            }
        },
        {
            "type": "Feature",
            "geometry": {
                "type": "Point",
                "sm_coordinates": "no",
                "coordinates": [
                    116.05698,
                    -32.14418
                ]
            },
            "properties": {
                "feedType": "incident",
                "sourceTitle": "BEDFORDALE",
                "category": "fire",
                "subcategory": "burn off",
                "status": "active",
                "id": "2029064-481034",
                "created": "2020-05-18T12:06:51+08:00",
                "updated": "2020-05-18T12:06:51+08:00",
                "location": "BEDFORDALE",
                "size": "",
                "description": "Burn Off",
                "title": "incident: fire"
            }
        },
        {
            "type": "Feature",
            "geometry": {
                "type": "Point",
                "sm_coordinates": "no",
                "coordinates": [
                    115.93641,
                    -32.50824
                ]
            },
            "properties": {
                "feedType": "incident",
                "sourceTitle": "NORTH DANDALUP",
                "category": "fire",
                "subcategory": "burn off",
                "status": "active",
                "id": "2029130-481055",
                "created": "2020-05-18T13:47:55+08:00",
                "updated": "2020-05-18T13:47:55+08:00",
                "location": "NORTH DANDALUP",
                "size": "",
                "description": "Burn Off",
                "title": "incident: fire"
            }
        },
        {
            "type": "Feature",
            "geometry": {
                "type": "Point",
                "sm_coordinates": "no",
                "coordinates": [
                    115.63625,
                    -32.646202
                ]
            },
            "properties": {
                "feedType": "incident",
                "sourceTitle": "DAWESVILLE",
                "category": "fire",
                "subcategory": "burn off",
                "status": "active",
                "id": "2029217-481084",
                "created": "2020-05-18T15:34:02+08:00",
                "updated": "2020-05-18T15:34:02+08:00",
                "location": "DAWESVILLE",
                "size": "",
                "description": "Burn Off",
                "title": "incident: fire"
            }
        },
        {
            "type": "Feature",
            "geometry": {
                "type": "Point",
                "sm_coordinates": "no",
                "coordinates": [
                    115.6694,
                    -32.702515
                ]
            },
            "properties": {
                "feedType": "incident",
                "sourceTitle": "BOUVARD",
                "category": "fire",
                "subcategory": "burn off",
                "status": "active",
                "id": "2028955-481008",
                "created": "2020-05-18T10:10:32+08:00",
                "updated": "2020-05-18T10:10:32+08:00",
                "location": "BOUVARD",
                "size": "",
                "description": "Burn Off",
                "title": "incident: fire"
            }
        },
        {
            "type": "Feature",
            "geometry": {
                "type": "Point",
                "sm_coordinates": "no",
                "coordinates": [
                    116.06046,
                    -32.10012
                ]
            },
            "properties": {
                "feedType": "incident",
                "sourceTitle": "ROLEYSTONE",
                "category": "fire",
                "subcategory": "burn off",
                "status": "active",
                "id": "2029021-481025",
                "created": "2020-05-18T11:27:50+08:00",
                "updated": "2020-05-18T11:27:50+08:00",
                "location": "ROLEYSTONE",
                "size": "",
                "description": "Burn Off",
                "title": "incident: fire"
            }
        },
        {
            "type": "Feature",
            "geometry": {
                "type": "Point",
                "sm_coordinates": "no",
                "coordinates": [
                    115.78072,
                    -32.58488
                ]
            },
            "properties": {
                "feedType": "incident",
                "sourceTitle": "SOUTH YUNDERUP",
                "category": "fire",
                "subcategory": "burn off",
                "status": "active",
                "id": "2029004-481020",
                "created": "2020-05-18T11:01:18+08:00",
                "updated": "2020-05-18T11:01:47+08:00",
                "location": "SOUTH YUNDERUP",
                "size": "",
                "description": "Burn Off",
                "title": "incident: fire"
            }
        },
        {
            "type": "Feature",
            "geometry": {
                "type": "Point",
                "sm_coordinates": "no",
                "coordinates": [
                    115.88261,
                    -31.697258
                ]
            },
            "properties": {
                "feedType": "incident",
                "sourceTitle": "MARIGINIUP",
                "category": "fire",
                "subcategory": "burn off",
                "status": "active",
                "id": "2028991-481016",
                "created": "2020-05-18T10:47:01+08:00",
                "updated": "2020-05-18T10:47:01+08:00",
                "location": "MARIGINIUP",
                "size": "",
                "description": "Burn Off",
                "title": "incident: fire"
            }
        },
        {
            "type": "Feature",
            "geometry": {
                "type": "Point",
                "sm_coordinates": "no",
                "coordinates": [
                    116.08687,
                    -31.927183
                ]
            },
            "properties": {
                "feedType": "incident",
                "sourceTitle": "DARLINGTON",
                "category": "fire",
                "subcategory": "burn off",
                "status": "active",
                "id": "2029088-481045",
                "created": "2020-05-18T12:55:15+08:00",
                "updated": "2020-05-18T12:55:15+08:00",
                "location": "DARLINGTON",
                "size": "",
                "description": "Burn Off",
                "title": "incident: fire"
            }
        },
        {
            "type": "Feature",
            "geometry": {
                "type": "Point",
                "sm_coordinates": "no",
                "coordinates": [
                    115.85263,
                    -32.6853
                ]
            },
            "properties": {
                "feedType": "incident",
                "sourceTitle": "BLYTHEWOOD",
                "category": "fire",
                "subcategory": "burn off",
                "status": "active",
                "id": "2029032-481029",
                "created": "2020-05-18T11:43:07+08:00",
                "updated": "2020-05-18T11:43:07+08:00",
                "location": "BLYTHEWOOD",
                "size": "",
                "description": "Burn Off",
                "title": "incident: fire"
            }
        },
        {
            "type": "Feature",
            "geometry": {
                "type": "Point",
                "sm_coordinates": "no",
                "coordinates": [
                    117.83658,
                    -28.08867
                ]
            },
            "properties": {
                "feedType": "incident",
                "sourceTitle": "MOUNT MAGNET",
                "category": "road crash",
                "subcategory": "road crash",
                "status": "monitoring",
                "id": "2029151-481061",
                "created": "2020-05-18T14:07:42+08:00",
                "updated": "2020-05-18T15:38:50+08:00",
                "location": "MOUNT MAGNET",
                "size": "",
                "description": "Road Crash",
                "title": "incident: road crash"
            }
        },
        {
            "type": "Feature",
            "geometry": {
                "type": "Point",
                "sm_coordinates": "no",
                "coordinates": [
                    115.4003,
                    -33.68722
                ]
            },
            "properties": {
                "feedType": "incident",
                "sourceTitle": "YALYALUP",
                "category": "fire",
                "subcategory": "burn off",
                "status": "active",
                "id": "2029001-481019",
                "created": "2020-05-18T10:58:39+08:00",
                "updated": "2020-05-18T10:58:39+08:00",
                "location": "YALYALUP",
                "size": "",
                "description": "Burn Off",
                "title": "incident: fire"
            }
        },
        {
            "type": "Feature",
            "geometry": {
                "type": "Point",
                "sm_coordinates": "no",
                "coordinates": [
                    116.13933,
                    -31.884588
                ]
            },
            "properties": {
                "feedType": "incident",
                "sourceTitle": "PARKERVILLE",
                "category": "fire",
                "subcategory": "burn off",
                "status": "active",
                "id": "2029120-481053",
                "created": "2020-05-18T13:37:05+08:00",
                "updated": "2020-05-18T13:37:05+08:00",
                "location": "PARKERVILLE",
                "size": "",
                "description": "Burn Off",
                "title": "incident: fire"
            }
        },
        {
            "type": "Feature",
            "geometry": {
                "type": "Point",
                "sm_coordinates": "no",
                "coordinates": [
                    116.26151,
                    -31.791533
                ]
            },
            "properties": {
                "feedType": "incident",
                "sourceTitle": "GIDGEGANNUP",
                "category": "fire",
                "subcategory": "burn off",
                "status": "active",
                "id": "2029157-481065",
                "created": "2020-05-18T14:21:41+08:00",
                "updated": "2020-05-18T14:21:41+08:00",
                "location": "GIDGEGANNUP",
                "size": "",
                "description": "Burn Off",
                "title": "incident: fire"
            }
        },
        {
            "type": "Feature",
            "geometry": {
                "type": "Point",
                "sm_coordinates": "no",
                "coordinates": [
                    115.79706,
                    -33.06723
                ]
            },
            "properties": {
                "feedType": "incident",
                "sourceTitle": "UDUC",
                "category": "fire",
                "subcategory": "bushfire",
                "status": "responding",
                "id": "2029206-481080",
                "created": "2020-05-18T15:08:08+08:00",
                "updated": "2020-05-18T15:17:26+08:00",
                "location": "UDUC",
                "size": "",
                "description": "Bushfire",
                "title": "incident: fire"
            }
        },
        {
            "type": "Feature",
            "geometry": {
                "type": "Point",
                "sm_coordinates": "no",
                "coordinates": [
                    115.782265,
                    -31.688354
                ]
            },
            "properties": {
                "feedType": "incident",
                "sourceTitle": "CARRAMAR",
                "category": "fire",
                "subcategory": "burn off",
                "status": "active",
                "id": "2029068-481040",
                "created": "2020-05-18T12:26:13+08:00",
                "updated": "2020-05-18T12:26:13+08:00",
                "location": "CARRAMAR",
                "size": "",
                "description": "Burn Off",
                "title": "incident: fire"
            }
        },
        {
            "type": "Feature",
            "geometry": {
                "type": "Point",
                "sm_coordinates": "no",
                "coordinates": [
                    116.00743,
                    -31.347109
                ]
            },
            "properties": {
                "feedType": "incident",
                "sourceTitle": "MOOLIABEENEE",
                "category": "fire",
                "subcategory": "burn off",
                "status": "active",
                "id": "2029091-481047",
                "created": "2020-05-18T13:04:23+08:00",
                "updated": "2020-05-18T13:04:23+08:00",
                "location": "MOOLIABEENEE",
                "size": "",
                "description": "Burn Off",
                "title": "incident: fire"
            }
        },
        {
            "type": "Feature",
            "geometry": {
                "type": "Point",
                "sm_coordinates": "no",
                "coordinates": [
                    116.064445,
                    -32.168148
                ]
            },
            "properties": {
                "feedType": "incident",
                "sourceTitle": "BEDFORDALE",
                "category": "fire",
                "subcategory": "burn off",
                "status": "active",
                "id": "2029037-481031",
                "created": "2020-05-18T11:46:14+08:00",
                "updated": "2020-05-18T11:46:14+08:00",
                "location": "BEDFORDALE",
                "size": "",
                "description": "Burn Off",
                "title": "incident: fire"
            }
        },
        {
            "type": "Feature",
            "geometry": {
                "type": "Point",
                "sm_coordinates": "no",
                "coordinates": [
                    115.77943,
                    -31.697514
                ]
            },
            "properties": {
                "feedType": "incident",
                "sourceTitle": "CARRAMAR",
                "category": "fire",
                "subcategory": "burn off",
                "status": "active",
                "id": "2029100-481048",
                "created": "2020-05-18T13:10:56+08:00",
                "updated": "2020-05-18T13:10:56+08:00",
                "location": "CARRAMAR",
                "size": "",
                "description": "Burn Off",
                "title": "incident: fire"
            }
        },
        {
            "type": "Feature",
            "geometry": {
                "type": "Point",
                "sm_coordinates": "no",
                "coordinates": [
                    115.65709,
                    -32.69489
                ]
            },
            "properties": {
                "feedType": "incident",
                "sourceTitle": "BOUVARD",
                "category": "fire",
                "subcategory": "burn off",
                "status": "active",
                "id": "2029185-481074",
                "created": "2020-05-18T14:53:37+08:00",
                "updated": "2020-05-18T14:53:37+08:00",
                "location": "BOUVARD",
                "size": "",
                "description": "Burn Off",
                "title": "incident: fire"
            }
        },
        {
            "type": "Feature",
            "geometry": {
                "type": "Point",
                "sm_coordinates": "no",
                "coordinates": [
                    116.18265,
                    -31.918304
                ]
            },
            "properties": {
                "feedType": "incident",
                "sourceTitle": "MUNDARING",
                "category": "fire",
                "subcategory": "burn off",
                "status": "active",
                "id": "2029067-481038",
                "created": "2020-05-18T12:13:40+08:00",
                "updated": "2020-05-18T12:13:40+08:00",
                "location": "MUNDARING",
                "size": "",
                "description": "Burn Off",
                "title": "incident: fire"
            }
        },
        {
            "type": "Feature",
            "geometry": {
                "type": "Point",
                "sm_coordinates": "no",
                "coordinates": [
                    116.15236,
                    -31.8272
                ]
            },
            "properties": {
                "feedType": "incident",
                "sourceTitle": "GIDGEGANNUP",
                "category": "fire",
                "subcategory": "burn off",
                "status": "active",
                "id": "2029171-481068",
                "created": "2020-05-18T14:35:07+08:00",
                "updated": "2020-05-18T14:35:07+08:00",
                "location": "GIDGEGANNUP",
                "size": "",
                "description": "Burn Off",
                "title": "incident: fire"
            }
        },
        {
            "type": "Feature",
            "geometry": {
                "type": "Point",
                "sm_coordinates": "no",
                "coordinates": [
                    116.16525,
                    -31.858622
                ]
            },
            "properties": {
                "feedType": "incident",
                "sourceTitle": "STONEVILLE",
                "category": "fire",
                "subcategory": "burn off",
                "status": "active",
                "id": "2029167-481067",
                "created": "2020-05-18T14:34:07+08:00",
                "updated": "2020-05-18T14:34:07+08:00",
                "location": "STONEVILLE",
                "size": "",
                "description": "Burn Off",
                "title": "incident: fire"
            }
        },
        {
            "type": "Feature",
            "geometry": {
                "type": "Point",
                "sm_coordinates": "no",
                "coordinates": [
                    116.080696,
                    -31.660269
                ]
            },
            "properties": {
                "feedType": "incident",
                "sourceTitle": "BULLSBROOK",
                "category": "fire",
                "subcategory": "burn off",
                "status": "active",
                "id": "2029137-481057",
                "created": "2020-05-18T13:57:25+08:00",
                "updated": "2020-05-18T13:57:25+08:00",
                "location": "BULLSBROOK",
                "size": "",
                "description": "Burn Off",
                "title": "incident: fire"
            }
        },
        {
            "type": "Feature",
            "geometry": {
                "type": "Point",
                "sm_coordinates": "no",
                "coordinates": [
                    116.22531,
                    -31.88802
                ]
            },
            "properties": {
                "feedType": "incident",
                "sourceTitle": "SAWYERS VALLEY",
                "category": "fire",
                "subcategory": "burn off",
                "status": "active",
                "id": "2029138-481058",
                "created": "2020-05-18T13:58:03+08:00",
                "updated": "2020-05-18T13:58:03+08:00",
                "location": "SAWYERS VALLEY",
                "size": "",
                "description": "Burn Off",
                "title": "incident: fire"
            }
        },
        {
            "type": "Feature",
            "geometry": {
                "type": "Point",
                "sm_coordinates": "no",
                "coordinates": [
                    115.79123,
                    -32.49219
                ]
            },
            "properties": {
                "feedType": "incident",
                "sourceTitle": "STAKE HILL",
                "category": "fire",
                "subcategory": "burn off",
                "status": "active",
                "id": "2029154-481063",
                "created": "2020-05-18T14:14:44+08:00",
                "updated": "2020-05-18T14:14:44+08:00",
                "location": "STAKE HILL",
                "size": "",
                "description": "Burn Off",
                "title": "incident: fire"
            }
        },
        {
            "type": "Feature",
            "geometry": {
                "type": "Point",
                "sm_coordinates": "no",
                "coordinates": [
                    116.125755,
                    -31.833113
                ]
            },
            "properties": {
                "feedType": "incident",
                "sourceTitle": "GIDGEGANNUP",
                "category": "fire",
                "subcategory": "burn off",
                "status": "active",
                "id": "2029193-481076",
                "created": "2020-05-18T15:03:27+08:00",
                "updated": "2020-05-18T15:03:27+08:00",
                "location": "GIDGEGANNUP",
                "size": "",
                "description": "Burn Off",
                "title": "incident: fire"
            }
        },
        {
            "type": "Feature",
            "geometry": {
                "type": "Point",
                "sm_coordinates": "no",
                "coordinates": [
                    116.02981,
                    -31.72509
                ]
            },
            "properties": {
                "feedType": "incident",
                "sourceTitle": "BULLSBROOK",
                "category": "fire",
                "subcategory": "burn off",
                "status": "active",
                "id": "2029201-481079",
                "created": "2020-05-18T15:07:06+08:00",
                "updated": "2020-05-18T15:07:06+08:00",
                "location": "BULLSBROOK",
                "size": "",
                "description": "Burn Off",
                "title": "incident: fire"
            }
        },
        {
            "type": "Feature",
            "geometry": {
                "type": "Point",
                "sm_coordinates": "no",
                "coordinates": [
                    116.03443,
                    -31.702662
                ]
            },
            "properties": {
                "feedType": "incident",
                "sourceTitle": "BULLSBROOK",
                "category": "fire",
                "subcategory": "burn off",
                "status": "active",
                "id": "2029195-481077",
                "created": "2020-05-18T15:05:28+08:00",
                "updated": "2020-05-18T15:05:28+08:00",
                "location": "BULLSBROOK",
                "size": "",
                "description": "Burn Off",
                "title": "incident: fire"
            }
        },
        {
            "type": "Feature",
            "geometry": {
                "type": "Point",
                "sm_coordinates": "no",
                "coordinates": [
                    128.69034,
                    -15.803675
                ]
            },
            "properties": {
                "feedType": "incident",
                "sourceTitle": "KUNUNURRA",
                "category": "fire",
                "subcategory": "burn off",
                "status": "active",
                "id": "2029141-481060",
                "created": "2020-05-18T14:00:28+08:00",
                "updated": "2020-05-18T14:01:38+08:00",
                "location": "KUNUNURRA",
                "size": "",
                "description": "Burn Off",
                "title": "incident: fire"
            }
        },
        {
            "type": "Feature",
            "geometry": {
                "type": "Point",
                "sm_coordinates": "no",
                "coordinates": [
                    116.085464,
                    -31.467173
                ]
            },
            "properties": {
                "feedType": "incident",
                "sourceTitle": "CHITTERING",
                "category": "fire",
                "subcategory": "burn off",
                "status": "active",
                "id": "2029162-481066",
                "created": "2020-05-18T14:27:59+08:00",
                "updated": "2020-05-18T14:27:59+08:00",
                "location": "CHITTERING",
                "size": "",
                "description": "Burn Off",
                "title": "incident: fire"
            }
        },
        {
            "type": "Feature",
            "geometry": {
                "type": "Point",
                "sm_coordinates": "no",
                "coordinates": [
                    116.073555,
                    -31.557968
                ]
            },
            "properties": {
                "feedType": "incident",
                "sourceTitle": "LOWER CHITTERING",
                "category": "fire",
                "subcategory": "burn off",
                "status": "active",
                "id": "2029222-481085",
                "created": "2020-05-18T15:37:17+08:00",
                "updated": "2020-05-18T15:37:25+08:00",
                "location": "LOWER CHITTERING",
                "size": "",
                "description": "Burn Off",
                "title": "incident: fire"
            }
        },
        {
            "type": "Feature",
            "geometry": {
                "type": "Point",
                "sm_coordinates": "no",
                "coordinates": [
                    116.21863,
                    -31.880756
                ]
            },
            "properties": {
                "feedType": "incident",
                "sourceTitle": "MOUNT HELENA",
                "category": "fire",
                "subcategory": "burn off",
                "status": "active",
                "id": "2029202-481081",
                "created": "2020-05-18T15:13:19+08:00",
                "updated": "2020-05-18T15:13:19+08:00",
                "location": "MOUNT HELENA",
                "size": "",
                "description": "Burn Off",
                "title": "incident: fire"
            }
        },
        {
            "type": "Feature",
            "geometry": {
                "type": "Point",
                "sm_coordinates": "no",
                "coordinates": [
                    116.17569,
                    -31.699808
                ]
            },
            "properties": {
                "feedType": "incident",
                "sourceTitle": "GIDGEGANNUP",
                "category": "fire",
                "subcategory": "burn off",
                "status": "active",
                "id": "2029153-481062",
                "created": "2020-05-18T14:09:43+08:00",
                "updated": "2020-05-18T14:09:43+08:00",
                "location": "GIDGEGANNUP",
                "size": "",
                "description": "Burn Off",
                "title": "incident: fire"
            }
        },
        {
            "type": "Feature",
            "geometry": {
                "type": "Point",
                "sm_coordinates": "no",
                "coordinates": [
                    115.80935,
                    -32.2268
                ]
            },
            "properties": {
                "feedType": "incident",
                "sourceTitle": "POSTANS",
                "category": "fire",
                "subcategory": "bushfire",
                "status": "on scene",
                "id": "2029186-481075",
                "created": "2020-05-18T14:55:17+08:00",
                "updated": "2020-05-18T15:27:24+08:00",
                "location": "POSTANS",
                "size": "",
                "description": "Bushfire",
                "title": "incident: fire"
            }
        },
        {
            "type": "Feature",
            "geometry": {
                "type": "Point",
                "sm_coordinates": "no",
                "coordinates": [
                    116.067535,
                    -31.624176
                ]
            },
            "properties": {
                "feedType": "incident",
                "sourceTitle": "BULLSBROOK",
                "category": "fire",
                "subcategory": "burn off",
                "status": "active",
                "id": "2029210-481082",
                "created": "2020-05-18T15:21:04+08:00",
                "updated": "2020-05-18T15:21:04+08:00",
                "location": "BULLSBROOK",
                "size": "",
                "description": "Burn Off",
                "title": "incident: fire"
            }
        },
        {
            "type": "Feature",
            "geometry": {
                "type": "Point",
                "sm_coordinates": "no",
                "coordinates": [
                    118.1354,
                    -22.64085
                ]
            },
            "properties": {
                "feedType": "incident",
                "sourceTitle": "KARIJINI",
                "category": "fire",
                "subcategory": "bushfire",
                "status": "monitoring",
                "id": "2018668-476325",
                "created": "2020-05-01T16:16:05+08:00",
                "updated": "2020-05-17T17:42:18+08:00",
                "location": "KARIJINI",
                "size": "",
                "description": "Bushfire",
                "title": "incident: fire"
            }
        },
        {
            "type": "Feature",
            "geometry": {
                "type": "Point",
                "sm_coordinates": "no",
                "coordinates": [
                    115.08361,
                    -33.638256
                ]
            },
            "properties": {
                "feedType": "incident",
                "sourceTitle": "QUEDJINUP",
                "category": "fire",
                "subcategory": "burn off",
                "status": "active",
                "id": "2024718-478960",
                "created": "2020-05-12T08:56:13+08:00",
                "updated": "2020-05-12T08:56:13+08:00",
                "location": "QUEDJINUP",
                "size": "",
                "description": "Burn Off",
                "title": "incident: fire"
            }
        },
        {
            "type": "Feature",
            "geometry": {
                "type": "Point",
                "sm_coordinates": "no",
                "coordinates": [
                    116.19617,
                    -31.11085
                ]
            },
            "properties": {
                "feedType": "incident",
                "sourceTitle": "WANNAMAL",
                "category": "fire",
                "subcategory": "burn off",
                "status": "active",
                "id": "2024950-479074",
                "created": "2020-05-12T13:51:19+08:00",
                "updated": "2020-05-12T13:51:19+08:00",
                "location": "WANNAMAL",
                "size": "",
                "description": "Burn Off",
                "title": "incident: fire"
            }
        },
        {
            "type": "Feature",
            "geometry": {
                "type": "Point",
                "sm_coordinates": "no",
                "coordinates": [
                    115.371315,
                    -33.676697
                ]
            },
            "properties": {
                "feedType": "incident",
                "sourceTitle": "BOVELL",
                "category": "fire",
                "subcategory": "burn off",
                "status": "active",
                "id": "2026299-479661",
                "created": "2020-05-14T11:52:08+08:00",
                "updated": "2020-05-14T11:52:08+08:00",
                "location": "BOVELL",
                "size": "",
                "description": "Burn Off",
                "title": "incident: fire"
            }
        },
        {
            "type": "Feature",
            "geometry": {
                "type": "Point",
                "sm_coordinates": "no",
                "coordinates": [
                    115.20699,
                    -33.769688
                ]
            },
            "properties": {
                "feedType": "incident",
                "sourceTitle": "KALOORUP",
                "category": "fire",
                "subcategory": "burn off",
                "status": "active",
                "id": "2026352-479682",
                "created": "2020-05-14T12:47:09+08:00",
                "updated": "2020-05-14T12:47:09+08:00",
                "location": "KALOORUP",
                "size": "",
                "description": "Burn Off",
                "title": "incident: fire"
            }
        },
        {
            "type": "Feature",
            "geometry": {
                "type": "Point",
                "sm_coordinates": "no",
                "coordinates": [
                    115.94528,
                    -33.74293
                ]
            },
            "properties": {
                "feedType": "incident",
                "sourceTitle": "MULLALYUP",
                "category": "fire",
                "subcategory": "burn off",
                "status": "active",
                "id": "2027783-480390",
                "created": "2020-05-16T12:04:07+08:00",
                "updated": "2020-05-16T12:04:07+08:00",
                "location": "MULLALYUP",
                "size": "",
                "description": "Burn Off",
                "title": "incident: fire"
            }
        },
        {
            "type": "Feature",
            "geometry": {
                "type": "Point",
                "sm_coordinates": "no",
                "coordinates": [
                    118.936,
                    -21.108
                ]
            },
            "properties": {
                "feedType": "incident",
                "sourceTitle": "MARBLE BAR",
                "category": "fire",
                "subcategory": "bushfire",
                "status": "monitoring",
                "id": "2026875-479900",
                "created": "2020-05-15T08:27:45+08:00",
                "updated": "2020-05-15T10:05:57+08:00",
                "location": "MARBLE BAR",
                "size": "",
                "description": "Bushfire",
                "title": "incident: fire"
            }
        },
        {
            "type": "Feature",
            "geometry": {
                "type": "Point",
                "sm_coordinates": "no",
                "coordinates": [
                    115.115486,
                    -33.646263
                ]
            },
            "properties": {
                "feedType": "incident",
                "sourceTitle": "QUINDALUP",
                "category": "fire",
                "subcategory": "burn off",
                "status": "active",
                "id": "2027643-480290",
                "created": "2020-05-16T09:14:57+08:00",
                "updated": "2020-05-16T09:14:57+08:00",
                "location": "QUINDALUP",
                "size": "",
                "description": "Burn Off",
                "title": "incident: fire"
            }
        },
        {
            "type": "Feature",
            "geometry": {
                "type": "Point",
                "sm_coordinates": "no",
                "coordinates": [
                    115.88625,
                    -31.36068
                ]
            },
            "properties": {
                "feedType": "incident",
                "sourceTitle": "COONABIDGEE",
                "category": "fire",
                "subcategory": "bushfire",
                "status": "monitoring",
                "id": "2026220-479626",
                "created": "2020-05-14T10:29:04+08:00",
                "updated": "2020-05-18T07:39:44+08:00",
                "location": "COONABIDGEE",
                "size": "",
                "description": "Bushfire",
                "title": "incident: fire"
            }
        },
        {
            "type": "Feature",
            "geometry": {
                "type": "Point",
                "sm_coordinates": "no",
                "coordinates": [
                    122.2309,
                    -17.8667
                ]
            },
            "properties": {
                "feedType": "incident",
                "sourceTitle": "WATERBANK",
                "category": "fire",
                "subcategory": "bushfire",
                "status": "monitoring",
                "id": "2028271-480708",
                "created": "2020-05-17T03:17:01+08:00",
                "updated": "2020-05-17T17:41:12+08:00",
                "location": "WATERBANK",
                "size": "",
                "description": "Bushfire",
                "title": "incident: fire"
            }
        },
        {
            "type": "Feature",
            "geometry": {
                "type": "Point",
                "sm_coordinates": "no",
                "coordinates": [
                    115.903984,
                    -33.539425
                ]
            },
            "properties": {
                "feedType": "incident",
                "sourceTitle": "QUEENWOOD",
                "category": "fire",
                "subcategory": "burn off",
                "status": "active",
                "id": "2028589-480872",
                "created": "2020-05-17T15:18:00+08:00",
                "updated": "2020-05-17T15:18:00+08:00",
                "location": "QUEENWOOD",
                "size": "",
                "description": "Burn Off",
                "title": "incident: fire"
            }
        },
        {
            "type": "Feature",
            "geometry": {
                "type": "Point",
                "sm_coordinates": "no",
                "coordinates": [
                    115.63896,
                    -31.329233
                ]
            },
            "properties": {
                "feedType": "incident",
                "sourceTitle": "NEERGABBY",
                "category": "fire",
                "subcategory": "burn off",
                "status": "active",
                "id": "2027839-480422",
                "created": "2020-05-16T13:02:19+08:00",
                "updated": "2020-05-16T13:02:19+08:00",
                "location": "NEERGABBY",
                "size": "",
                "description": "Burn Off",
                "title": "incident: fire"
            }
        },
        {
            "type": "Feature",
            "geometry": {
                "type": "Point",
                "sm_coordinates": "no",
                "coordinates": [
                    115.26722,
                    -33.80681
                ]
            },
            "properties": {
                "feedType": "incident",
                "sourceTitle": "BOALLIA",
                "category": "fire",
                "subcategory": "bushfire",
                "status": "monitoring",
                "id": "2028580-480865",
                "created": "2020-05-17T15:03:49+08:00",
                "updated": "2020-05-18T08:24:55+08:00",
                "location": "BOALLIA",
                "size": "",
                "description": "Bushfire",
                "title": "incident: fire"
            }
        }
    ]
}